JayttleProcess/CommonDecorator.py
JayttleProcess/ComputerControl.py
JayttleProcess/EmailsmtplibUse.py
JayttleProcess/EntertainmentCode.py
JayttleProcess/FTPCommonUse.py
JayttleProcess/JsonCommonManage.py
JayttleProcess/ListFloatDataMethod.py
JayttleProcess/MachineLearning.py
JayttleProcess/PNGProcess.py
JayttleProcess/PredictiveModel.py
JayttleProcess/RinexCommonManage.py
JayttleProcess/SQLCommonUse.py
JayttleProcess/TBCProcessCsv.py
JayttleProcess/TiltmeterCommonUse.py
JayttleProcess/TimeDataFrameMethod.py
JayttleProcess/TimeSeriesDataMethod.py
JayttleProcess/WebsiteCrawler.py
JayttleProcess/__init__.py
JayttleProcess-0.4.2.dist-info/METADATA
JayttleProcess-0.4.2.dist-info/WHEEL
JayttleProcess-0.4.2.dist-info/top_level.txt
JayttleProcess-0.4.2.dist-info/RECORD
